aqman/__init__.py
aqman/__version__.py
aqman/aqman.py
aqman/const.py
aqman/exceptions.py
aqman/models.py
python_aqman-0.2.1.dist-info/LICENSE
python_aqman-0.2.1.dist-info/METADATA
python_aqman-0.2.1.dist-info/WHEEL
python_aqman-0.2.1.dist-info/top_level.txt
python_aqman-0.2.1.dist-info/RECORD
