Metadata-Version: 2.1
Name: python-aqman
Version: 0.2.1
Summary: Asynchronous Python Client for Radon FTLabs AQMAN101
Home-page: https://github.com/hkder/python-aqman
Author: Hosung Kim
Author-email: samhskim1@gmail.com
License: MIT license
Platform: UNKNOWN
Classifier: Programming Language :: Python :: 3.7
Classifier: Programming Language :: Python :: 3.8
Classifier: License :: OSI Approved :: MIT License
Classifier: Operating System :: OS Independent
Requires-Python: >=3.7
Requires-Dist: aiohttp (>=3.0.0)
Requires-Dist: attrs (>=19.0.0)
Requires-Dist: yarl (>=1.0.0)
